pattingalloang/__init__.py
pattingalloang/cli.py
pattingalloang/core/__init__.py
pattingalloang/core/attractor.py
pattingalloang/core/integrator.py
pattingalloang/core/metrics.py
pattingalloang/io/__init__.py
pattingalloang/io/config_manager.py
pattingalloang/io/data_handler.py
pattingalloang/utils/__init__.py
pattingalloang/utils/logger.py
pattingalloang/utils/timer.py
pattingalloang/visualization/__init__.py
pattingalloang/visualization/animator.py
pattingalloang-0.0.2.dist-info/METADATA
pattingalloang-0.0.2.dist-info/WHEEL
pattingalloang-0.0.2.dist-info/entry_points.txt
pattingalloang-0.0.2.dist-info/licenses/LICENSE
pattingalloang-0.0.2.dist-info/RECORD
