Metadata-Version: 2.4
Name: pattingalloang
Version: 0.0.2
Summary: JAX-Accelerated Aizawa Attractor Analysis with Comprehensive Chaos Metrics
License: MIT
License-File: LICENSE
Keywords: chaos,attractor,dynamical-systems,jax,lyapunov,nonlinear-dynamics
Author: Sandy H. S. Herho
Author-email: sandy.herho@email.ucr.edu
Requires-Python: >=3.9,<4.0
Classifier: Development Status :: 4 - Beta
Classifier: Intended Audience :: Science/Research
Classifier: License :: OSI Approved :: MIT License
Classifier: Operating System :: OS Independent
Classifier: Programming Language :: Python :: 3
Classifier: Programming Language :: Python :: 3.9
Classifier: Programming Language :: Python :: 3.10
Classifier: Programming Language :: Python :: 3.11
Classifier: Programming Language :: Python :: 3.12
Classifier: Programming Language :: Python :: 3.13
Classifier: Programming Language :: Python :: 3.14
Classifier: Topic :: Scientific/Engineering :: Mathematics
Classifier: Topic :: Scientific/Engineering :: Physics
Classifier: Topic :: Scientific/Engineering :: Visualization
Requires-Dist: Pillow (>=9.0.0)
Requires-Dist: jax (>=0.4.0)
Requires-Dist: jaxlib (>=0.4.0)
Requires-Dist: matplotlib (>=3.5.0)
Requires-Dist: netCDF4 (>=1.5.0)
Requires-Dist: numpy (>=1.20.0)
Requires-Dist: pandas (>=1.3.0)
Requires-Dist: scipy (>=1.7.0)
Requires-Dist: tqdm (>=4.60.0)
Project-URL: Homepage, https://github.com/sandyherho/pattingalloang
Project-URL: Repository, https://github.com/sandyherho/pattingalloang
